CoAPthon3-1.0.2.data/scripts/coapclient.py
CoAPthon3-1.0.2.data/scripts/coapforwardproxy.py
CoAPthon3-1.0.2.data/scripts/coapreverseproxy.py
CoAPthon3-1.0.2.data/scripts/coapserver.py
CoAPthon3-1.0.2.data/scripts/exampleresources.py
coapthon/__init__.py
coapthon/defines.py
coapthon/serializer.py
coapthon/transaction.py
coapthon/utils.py
coapthon/caching/__init__.py
coapthon/caching/cache.py
coapthon/caching/coapcache.py
coapthon/caching/coaplrucache.py
coapthon/client/__init__.py
coapthon/client/coap.py
coapthon/client/helperclient.py
coapthon/forward_proxy/__init__.py
coapthon/forward_proxy/coap.py
coapthon/layers/__init__.py
coapthon/layers/blocklayer.py
coapthon/layers/cachelayer.py
coapthon/layers/forwardLayer.py
coapthon/layers/messagelayer.py
coapthon/layers/observelayer.py
coapthon/layers/requestlayer.py
coapthon/layers/resourcelayer.py
coapthon/messages/__init__.py
coapthon/messages/message.py
coapthon/messages/option.py
coapthon/messages/request.py
coapthon/messages/response.py
coapthon/resources/__init__.py
coapthon/resources/remoteResource.py
coapthon/resources/resource.py
coapthon/reverse_proxy/__init__.py
coapthon/reverse_proxy/coap.py
coapthon/server/__init__.py
coapthon/server/coap.py
CoAPthon3-1.0.2.dist-info/LICENSE
CoAPthon3-1.0.2.dist-info/METADATA
CoAPthon3-1.0.2.dist-info/WHEEL
CoAPthon3-1.0.2.dist-info/top_level.txt
CoAPthon3-1.0.2.dist-info/RECORD
